Metadata-Version: 2.1
Name: nltp
Version: 0.1.0
Summary: Simple  automated text preprocessor
Home-page: https://github.com/izzyx6/nltp
Author: Isreal Ufumaka
Author-email: isrealufumaka@gmail.com
License: UNKNOWN
Platform: UNKNOWN
Classifier: Programming Language :: Python :: 3
Classifier: License :: OSI Approved :: MIT License
Classifier: Operating System :: OS Independent
Requires-Python: >=3.6
